{
  "accentColor": "{{appsmith.theme.colors.primaryColor}}",
  "animateLoading": true,
  "borderRadius": "{{appsmith.theme.borderRadius.appBorderRadius}}",
  "bottomRow": 6,
  "boxShadow": "none",
  "defaultOptionValue": "\t",
  "dynamicBindingPathList": [
    {
      "key": "accentColor"
    },
    {
      "key": "borderRadius"
    },
    {
      "key": "sourceData"
    }
  ],
  "dynamicHeight": "FIXED",
  "dynamicPropertyPathList": [
    {
      "key": "sourceData"
    }
  ],
  "dynamicTriggerPathList": [],
  "isDisabled": false,
  "isFilterable": false,
  "isLoading": false,
  "isRequired": false,
  "isVisible": true,
  "key": "uy1byt93fp",
  "labelAlignment": "left",
  "labelPosition": "Top",
  "labelText": "Organisme",
  "labelTextSize": "0.875rem",
  "labelWidth": 5,
  "leftColumn": 25,
  "maxDynamicHeight": 9000,
  "minDynamicHeight": 4,
  "minWidth": 450,
  "mobileBottomRow": 6,
  "mobileLeftColumn": 25,
  "mobileRightColumn": 45,
  "mobileTopRow": 0,
  "needsErrorInfo": false,
  "optionLabel": "label",
  "optionValue": "value",
  "parentColumnSpace": 14.82568359375,
  "parentId": "59rw5mx0bq",
  "parentRowSpace": 10,
  "placeholderText": "Select option",
  "renderMode": "CANVAS",
  "responsiveBehavior": "fill",
  "rightColumn": 37,
  "serverSideFiltering": false,
  "sourceData": "{{liste_organ.data}}",
  "topRow": 0,
  "type": "SELECT_WIDGET",
  "version": 1,
  "widgetId": "fnpovlakdz",
  "widgetName": "filtre_organ"
}